scriptgen/__init__.py
scriptgen/core/__init__.py
scriptgen/core/_string_builder.py
scriptgen/core/_utils.py
scriptgen/templates/__init__.py
scriptgen/templates/csharp/__init__.py
scriptgen/templates/csharp/_csharp.py
scriptgen/templates/markdown/__init__.py
scriptgen/templates/markdown/_markdown.py
scriptgen/templates/xml/__init__.py
scriptgen/templates/xml/_xml.py
scriptgen-0.0.5.dist-info/LICENSE.txt
scriptgen-0.0.5.dist-info/METADATA
scriptgen-0.0.5.dist-info/WHEEL
scriptgen-0.0.5.dist-info/top_level.txt
scriptgen-0.0.5.dist-info/RECORD
