Metadata-Version: 2.1
Name: scriptgen
Version: 0.0.5
Summary: A collection of script generation helpers and templates.
Home-page: https://github.com/Fopoon/scriptgen
Author: Elmer Nocon, fopoon
Author-email: elmernocon@gmail.com
License: MIT
Download-URL: https://pypi.org/project/scriptgen/
Platform: Any
Classifier: Development Status :: 1 - Planning
Classifier: License :: OSI Approved :: MIT License
Classifier: Operating System :: MacOS :: MacOS X
Classifier: Operating System :: Microsoft :: Windows :: Windows 10
Classifier: Operating System :: Unix
Classifier: Programming Language :: Python :: 3
Classifier: Programming Language :: Python :: 3.7
Classifier: Programming Language :: Python :: 3 :: Only
